{
  "project_info": {
    "project_number": "200208948655",
    "firebase_url": "https://imei-scanner-d7ab3-default-rtdb.europe-west1.firebasedatabase.app",
    "project_id": "imei-scanner-d7ab3",
    "storage_bucket": "imei-scanner-d7ab3.appspot.com"
  },
  "client": [
    {
      "client_info": {
        "mobilesdk_app_id": "1:200208948655:android:2f095441dfeb728e3da35a",
        "android_client_info": {
          "package_name": "com.example.imeiscanner"
        }
      },
      "oauth_client": [
        {
          "client_id": "200208948655-ck5bs3mkgj1anhidu6e6br5moq5kvq1f.apps.googleusercontent.com",
          "client_type": 1,
          "android_info": {
            "package_name": "com.example.imeiscanner",
            "certificate_hash": "a43e2281f699247731f898c6157c23000434d703"
          }
        },
        {
          "client_id": "200208948655-ehtrhqqm7rqnuaprtvjgtq15b92kpgov.apps.googleusercontent.com",
          "client_type": 3
        }
      ],
      "api_key": [
        {
          "current_key": "AIzaSyBwFux6AEmKWSOtHhTLxVmCXNXdapgUURs"
        }
      ],
      "services": {
        "appinvite_service": {
          "other_platform_oauth_client": [
            {
              "client_id": "200208948655-ehtrhqqm7rqnuaprtvjgtq15b92kpgov.apps.googleusercontent.com",
              "client_type": 3
            }
          ]
        }
      }
    }
  ],
  "configuration_version": "1"
}